{
  "id": "qa-and-the-actual-importance-of-the-hare-krsna-chant-2c-is-that-in-saying-the-name-3f----or-is-it-a----continuous-flow-3f",
  "type": "qa",
  "title": "And the actual importance of the Hare Krsna chant, is that in saying the name?... Or is it a... continuous flow?",
  "subtitle": "Related questions",
  "date": "",
  "location": "",
  "speakers": [],
  "tags": [],
  "text": "Related questions",
  "sourceUrl": "https://vedabase.cc/en/qa/And_the_actual_importance_of_the_Hare_Krsna_chant%2C_is_that_in_saying_the_name%3F..._Or_is_it_a..._continuous_flow%3F/",
  "scrapedAt": "2026-07-23T21:22:17.206Z"
}