{
  "id": "qa-and-ah-2c-this-inside-2c-it-grows-because-of-krsna-does-it--anything-you-take-2c-it-grows-from-the-supreme--3f",
  "type": "qa",
  "title": "And ah, this inside, it grows because of Krsna does it (anything you take, it grows from the Supreme)?",
  "subtitle": "Related questions",
  "date": "",
  "location": "",
  "speakers": [],
  "tags": [],
  "text": "Related questions",
  "sourceUrl": "https://vedabase.cc/en/qa/And_ah%2C_this_inside%2C_it_grows_because_of_Krsna_does_it_(anything_you_take%2C_it_grows_from_the_Supreme)%3F/",
  "scrapedAt": "2026-07-23T21:20:40.597Z"
}